textbase_framework/__init__.py
textbase_framework/bot.py
textbase_framework/examples/huggingface-bot.py
textbase_framework/examples/mimic-bot.py
textbase_framework/examples/openai-bot.py
textbase_framework/message.py
textbase_framework/models.py
textbase_framework-0.1.3.dist-info/METADATA
textbase_framework-0.1.3.dist-info/WHEEL
textbase_framework-0.1.3.dist-info/RECORD
